<?xml version="1.0" encoding="utf-8"?>
<sqldata>
  <table name="comments">
    <field pk="1">
      <name>comment_id</name>
      <type>int(11)</type>
      <value null="0"></value>
      <extra>auto_increment</extra>
    </field>
    <field>
      <name>comment_text</name>
      <type>text</type>
      <value null="0"></value>
      <extra></extra>
    </field>
    <field>
      <name>comment_username</name>
      <type>varchar(100)</type>
      <value null="0"></value>
      <extra></extra>
    </field>
    <field>
      <name>comment_hook</name>
      <type>varchar(255)</type>
      <value null="0"></value>
      <extra></extra>
    </field>
    <field>
      <name>comment_time</name>
      <type>datetime</type>
      <value null="0"></value>
      <extra></extra>
    </field>
    <data/>
  </table>
</sqldata>
